minco/__init__.py
minco-1.1.dist-info/METADATA
minco-1.1.dist-info/WHEEL
minco-1.1.dist-info/top_level.txt
minco-1.1.dist-info/RECORD
