Metadata-Version: 2.4
Name: minco
Version: 1.1
Summary: minco
Author: Kanowara Sinoka
License: MIT
Project-URL: Homepage, https://github.com/sinokadev/minco
Requires-Python: >=3.0
